mri2mesh/__init__.py
mri2mesh/__main__.py
mri2mesh/cli.py
mri2mesh/constants.py
mri2mesh/morphology.py
mri2mesh/reader.py
mri2mesh/segmentation_labels.py
mri2mesh/vtk_utils.py
mri2mesh/mesh/__init__.py
mri2mesh/mesh/basic.py
mri2mesh/mesh/idealized_brain.py
mri2mesh/surface/__init__.py
mri2mesh/surface/idealized_brain.py
mri2mesh/surface/parenchyma.py
mri2mesh/surface/utils.py
mri2mesh/viz/__init__.py
mri2mesh/viz/mpl_slice.py
mri2mesh/viz/volume_clip.py
mri2mesh/viz/volume_slice.py
mri2mesh/viz/volume_threshold.py
mri2mesh-0.2.0.dist-info/licenses/LICENSE
mri2mesh-0.2.0.dist-info/METADATA
mri2mesh-0.2.0.dist-info/WHEEL
mri2mesh-0.2.0.dist-info/entry_points.txt
mri2mesh-0.2.0.dist-info/top_level.txt
mri2mesh-0.2.0.dist-info/RECORD
