Metadata-Version: 2.4
Name: mri2mesh
Version: 0.2.0
Summary: Tool for converting labeled MRI data to a mesh
Author-email: Henrik Finsberg <henriknf@simula.no>, Marius Causemann <mariusca@simula.no>
License: MIT
Project-URL: Homepage, https://github.com/scientificcomputing/mri2mesh
Keywords: mri,fem,brain,meshing
Classifier: License :: OSI Approved :: MIT License
Classifier: Programming Language :: Python :: 3
License-File: LICENSE
Requires-Dist: pyvista
Requires-Dist: numpy
Requires-Dist: matplotlib
Requires-Dist: nibabel
Requires-Dist: scikit-image
Requires-Dist: scipy
Requires-Dist: meshio
Provides-Extra: mesh
Requires-Dist: wildmeshing; extra == "mesh"
Requires-Dist: h5py; extra == "mesh"
Provides-Extra: test
Requires-Dist: pytest; extra == "test"
Requires-Dist: pytest-cov; extra == "test"
Requires-Dist: mri2mesh[mesh]; extra == "test"
Provides-Extra: docs
Requires-Dist: pyvista[jupyter]; extra == "docs"
Requires-Dist: jupyter-book; extra == "docs"
Requires-Dist: mri2mesh[mesh]; extra == "docs"
Dynamic: license-file
